pymoldyn/__init__.py
pymoldyn/__main__.py
pymoldyn/_version.py
pymoldyn/icon.png
pymoldyn/cli/__init__.py
pymoldyn/cli/cli.py
pymoldyn/computation/__init__.py
pymoldyn/computation/split_and_merge/__init__.py
pymoldyn/computation/split_and_merge/algorithm.py
pymoldyn/computation/split_and_merge/pipeline.py
pymoldyn/computation/split_and_merge/domain_centers/__init__.py
pymoldyn/computation/split_and_merge/domain_centers/calculate_domain_centers.c
pymoldyn/computation/split_and_merge/domain_centers/calculate_domain_centers.cpython-39-darwin.so
pymoldyn/computation/split_and_merge/util/__init__.py
pymoldyn/computation/split_and_merge/util/graph.py
pymoldyn/computation/split_and_merge/util/node_border_iterator.py
pymoldyn/computation/split_and_merge/util/pos_bool_type.py
pymoldyn/computation/split_and_merge/util/prohibited.py
pymoldyn/computation/split_and_merge/util/numpy_extension/__init__.py
pymoldyn/computation/split_and_merge/util/numpy_extension/find_index_of_first_element_not_equivalent.c
pymoldyn/computation/split_and_merge/util/numpy_extension/find_index_of_first_element_not_equivalent.cpython-39-darwin.so
pymoldyn/config/__init__.py
pymoldyn/config/configobj.py
pymoldyn/config/configuration.py
pymoldyn/config/cutoff_history.py
pymoldyn/config/cutoff_presets.py
pymoldyn/config/validate.py
pymoldyn/core/__init__.py
pymoldyn/core/bonds.py
pymoldyn/core/control.py
pymoldyn/core/data.py
pymoldyn/core/elements.py
pymoldyn/core/file.py
pymoldyn/core/volumes.py
pymoldyn/core/calculation/__init__.py
pymoldyn/core/calculation/algorithm.py
pymoldyn/core/calculation/calculation.py
pymoldyn/core/calculation/discretization.py
pymoldyn/core/calculation/gyrationtensor.py
pymoldyn/core/calculation/extension/__init__.py
pymoldyn/core/calculation/extension/algorithm.c
pymoldyn/core/calculation/extension/extension_ctypes.py
pymoldyn/core/calculation/extension/extension_python.py
pymoldyn/core/calculation/extension/libalgorithm.dylib
pymoldyn/gui/__init__.py
pymoldyn-0.11.1.dist-info/licenses/LICENSE
pymoldyn-0.11.1.dist-info/METADATA
pymoldyn-0.11.1.dist-info/WHEEL
pymoldyn-0.11.1.dist-info/entry_points.txt
pymoldyn-0.11.1.dist-info/top_level.txt
pymoldyn-0.11.1.dist-info/RECORD
