Metadata-Version: 2.4
Name: pyMolDyn
Version: 0.11.1
Summary: A molecule viewer with cavity computation.
Author: David Knodt, Florian Macherey
Author-email: Florian Rhiem <f.rhiem@fz-juelich.de>, Fabian Beule <f.beule@fz-juelich.de>, Ingo Meyer <i.meyer@fz-juelich.de>, Torben Moll <t.moll@fz-juelich.de>
Maintainer-email: Ingo Meyer <i.meyer@fz-juelich.de>
License: Copyright 2015-2024 Forschungszentrum Jülich GmbH
Project-URL: Homepage, https://pgi-jcns.fz-juelich.de/portal/pages/pymoldyn-main.html
Keywords: scientific
Classifier: Development Status :: 5 - Production/Stable
Classifier: Environment :: Console
Classifier: Intended Audience :: Science/Research
Classifier: License :: OSI Approved :: MIT License
Classifier: Natural Language :: English
Classifier: Operating System :: MacOS
Classifier: Operating System :: Microsoft :: Windows
Classifier: Operating System :: POSIX :: Linux
Classifier: Programming Language :: C
Classifier: Programming Language :: Python :: 3
Classifier: Programming Language :: Python :: 3 :: Only
Classifier: Programming Language :: Python :: 3.9
Classifier: Programming Language :: Python :: 3.10
Classifier: Programming Language :: Python :: 3.11
Classifier: Programming Language :: Python :: 3.12
Classifier: Topic :: Scientific/Engineering :: Physics
Classifier: Topic :: Scientific/Engineering :: Visualization
Requires-Python: >=3.9
License-File: LICENSE
Requires-Dist: gr
Requires-Dist: h5py
Requires-Dist: Jinja2
Requires-Dist: numpy
Requires-Dist: PyOpenGL
Requires-Dist: PySide6
Requires-Dist: python-dateutil
Dynamic: license-file
